i2cylib/__init__.py
i2cylib/crypto/__init__.py
i2cylib/crypto/I2En/__init__.py
i2cylib/crypto/I2En/icen.py
i2cylib/crypto/iccode/__init__.py
i2cylib/crypto/iccode/iccode.py
i2cylib/crypto/keygen/__init__.py
i2cylib/crypto/keygen/dynkey.py
i2cylib/crypto/keygen/dynkey2.py
i2cylib/crypto/keygen/time_key.py
i2cylib/crypto/utils/__init__.py
i2cylib/crypto/utils/operators.py
i2cylib/database/__init__.py
i2cylib/database/I2DB/__init__.py
i2cylib/database/I2DB/i2cydbclient.py
i2cylib/database/I2DB/i2cydbserver.py
i2cylib/database/sqlite/__init__.py
i2cylib/database/sqlite/sqlitedb.py
i2cylib/engineering/__init__.py
i2cylib/engineering/pid.py
i2cylib/filesystem/__init__.py
i2cylib/filesystem/icfat64/__init__.py
i2cylib/filesystem/icfat64/icfat.py
i2cylib/hid/__init__.py
i2cylib/hid/anotc/__init__.py
i2cylib/hid/anotc/ofs.py
i2cylib/hid/utils/__init__.py
i2cylib/network/__init__.py
i2cylib/network/I2Scan/__init__.py
i2cylib/network/I2Scan/i2scan.py
i2cylib/network/I2TCP/__init__.py
i2cylib/network/I2TCP/client.py
i2cylib/network/I2TCP/server.py
i2cylib/network/I2TCP/test.py
i2cylib/network/__I2Pipe/__init__.py
i2cylib/network/__I2Pipe/pipe.py
i2cylib/network/i2tcp_basic/__init__.py
i2cylib/network/i2tcp_basic/base_client.py
i2cylib/network/i2tcp_basic/base_server.py
i2cylib/science/__init__.py
i2cylib/science/test.py
i2cylib/science/plot/__init__.py
i2cylib/science/plot/plot.py
i2cylib/serial/__init__.py
i2cylib/serial/HTprot/__init__.py
i2cylib/serial/HTprot/htsocket.py
i2cylib/serial/sbus/__init__.py
i2cylib/serial/utils/__init__.py
i2cylib/serial/utils/device_scanner.py
i2cylib/utils/__init__.py
i2cylib/utils/args/__init__.py
i2cylib/utils/args/decode_args.py
i2cylib/utils/args/get_args.py
i2cylib/utils/bytes/__init__.py
i2cylib/utils/bytes/data_transform.py
i2cylib/utils/bytes/random_bytesgen.py
i2cylib/utils/delay/__init__.py
i2cylib/utils/delay/normal_delay.py
i2cylib/utils/files/__init__.py
i2cylib/utils/files/hash_file.py
i2cylib/utils/files/import_scripts.py
i2cylib-1.13.14.dist-info/LICENSE
i2cylib-1.13.14.dist-info/METADATA
i2cylib-1.13.14.dist-info/WHEEL
i2cylib-1.13.14.dist-info/entry_points.txt
i2cylib-1.13.14.dist-info/top_level.txt
i2cylib-1.13.14.dist-info/RECORD
