Metadata-Version: 2.1
Name: i2cylib
Version: 1.13.14
Summary: A Python library contains a lot of useful functions and tools
Home-page: https://github.com/i2cy/i2cylib
Author: I2cy Cloud
Author-email: i2cy@outlook.com
License: UNKNOWN
Project-URL: Bug Tracker, https://github.com/i2cy/i2cylib/issues
Project-URL: Source Code, https://github.com/i2cy/i2cylib
Project-URL: Documentation, https://github.com/i2cy/I2cylib/wiki/API-Document
Platform: UNKNOWN
Classifier: Programming Language :: Python :: 3
Classifier: License :: OSI Approved :: MIT License
Classifier: Operating System :: OS Independent
Requires-Python: >=3.6
License-File: LICENSE
Requires-Dist: numpy
Requires-Dist: tqdm
Requires-Dist: rsa
Requires-Dist: pyserial
Requires-Dist: matplotlib
Requires-Dist: hidapi
